CHANGELOG.rst
DESCRIPTION.rst
MANIFEST.in
README.rst
addqueries
setup.py
hcpreq/__init__.py
hcpreq/__main__.py
hcpreq/db.py
hcpreq/logs.py
hcpreq/queries
hcpreq/queries.py
hcpreq/xlsx.py
hcprequestanalytics.egg-info/PKG-INFO
hcprequestanalytics.egg-info/SOURCES.txt
hcprequestanalytics.egg-info/dependency_links.txt
hcprequestanalytics.egg-info/entry_points.txt
hcprequestanalytics.egg-info/requires.txt
hcprequestanalytics.egg-info/top_level.txt
version/__init__.py