Metadata-Version: 1.1
Name: hcprequestanalytics
Version: 1.3.7
Summary: hcprequestanalytics - analyze HCP HTTP request logs
Home-page: https://gitlab.com/simont3/hcprequestanalytics
Author: Thorsten Simons
Author-email: sw@snomis.de
License: MIT
Keywords: HCP access request http log Hitachi Content Platform
Platform: UNKNOWN
Classifier: Development Status :: 5 - Production/Stable
Classifier: Intended Audience :: System Administrators
Classifier: Topic :: System :: Archiving
Classifier: Topic :: System :: Logging
Classifier: License :: OSI Approved :: MIT License
Classifier: Programming Language :: Python :: 3.4
Classifier: Programming Language :: Python :: 3.5
Classifier: Programming Language :: Python :: 3.6
Classifier: Operating System :: OS Independent
Classifier: Natural Language :: English
